sol_instruct/__init__.py
sol_instruct-1.0.4.dist-info/METADATA
sol_instruct-1.0.4.dist-info/WHEEL
sol_instruct-1.0.4.dist-info/RECORD
