Metadata-Version: 2.1
Name: sol_instruct
Version: 1.0.4
Summary: Instructions library for Solana tokens in Python. Contains common program IDs, contract layouts, and types.
Author: bizkie
Requires-Python: >=3.10,<4.0
Classifier: Programming Language :: Python :: 3
Classifier: Programming Language :: Python :: 3.10
Classifier: Programming Language :: Python :: 3.11
Classifier: Programming Language :: Python :: 3.12
Requires-Dist: base58 (>=2.1.1,<3.0.0)
Requires-Dist: borsh-construct (>=0.1.0,<0.2.0)
Requires-Dist: requests (>=2.32.2,<3.0.0)
Requires-Dist: solana (>=0.34.0,<0.35.0)
Requires-Dist: solders (>=0.21.0,<0.22.0)
